geospatial_ml/__init__.py
geospatial_ml/geospatial_ml.py
geospatial_ml-0.1.2.dist-info/LICENSE
geospatial_ml-0.1.2.dist-info/METADATA
geospatial_ml-0.1.2.dist-info/WHEEL
geospatial_ml-0.1.2.dist-info/dependency_links.txt
geospatial_ml-0.1.2.dist-info/top_level.txt
geospatial_ml-0.1.2.dist-info/RECORD
