Metadata-Version: 2.1
Name: geospatial-ml
Version: 0.1.2
Summary: A collection of Python packages for geospatial analysis and machine learning.
Home-page: https://github.com/giswqs/geospatial-ml
Author: Qiusheng Wu
Author-email: giswqs@gmail.com
License: MIT license
Keywords: geospatial_ml
Platform: UNKNOWN
Classifier: Development Status :: 2 - Pre-Alpha
Classifier: Intended Audience :: Developers
Classifier: License :: OSI Approved :: MIT License
Classifier: Natural Language :: English
Classifier: Programming Language :: Python :: 3
Classifier: Programming Language :: Python :: 3.7
Classifier: Programming Language :: Python :: 3.8
Classifier: Programming Language :: Python :: 3.9
Requires-Python: >=3.7
License-File: LICENSE
Requires-Dist: geospatial
Requires-Dist: keras
Requires-Dist: localtileserver
Requires-Dist: torch
Requires-Dist: pytorch-lightning
Requires-Dist: rasterio
Requires-Dist: scikit-gstat
Requires-Dist: scikit-learn
Requires-Dist: scikit-plot
Requires-Dist: tensorflow
Requires-Dist: torchgeo
Requires-Dist: verde
